tropmi/__init__.py
tropmi-0.0.1.dist-info/LICENSE.txt
tropmi-0.0.1.dist-info/METADATA
tropmi-0.0.1.dist-info/WHEEL
tropmi-0.0.1.dist-info/top_level.txt
tropmi-0.0.1.dist-info/RECORD
